llama_index/llms/sagemaker_endpoint/__init__.py
llama_index/llms/sagemaker_endpoint/base.py
llama_index/llms/sagemaker_endpoint/utils.py
llama_index_llms_sagemaker_endpoint-0.4.2.dist-info/METADATA
llama_index_llms_sagemaker_endpoint-0.4.2.dist-info/WHEEL
llama_index_llms_sagemaker_endpoint-0.4.2.dist-info/licenses/LICENSE
llama_index_llms_sagemaker_endpoint-0.4.2.dist-info/RECORD
